inflame/__init__.py
inflame/__main__.py
inflame/data/__init__.py
inflame/data/util/__init__.py
inflame/data/util/embed.py
inflame/data/util/loader.py
inflame/models/__init__.py
inflame/models/bbcnews.py
inflame/models/newsgrp.py
inflame/params/__init__.py
inflame/params/bbcnews.py
inflame/params/newsgrp.py
inflame/train/__init__.py
inflame/train/train.py
inflame/train/validate.py
inflame-1.0.0.dist-info/LICENSE.md
inflame-1.0.0.dist-info/METADATA
inflame-1.0.0.dist-info/WHEEL
inflame-1.0.0.dist-info/entry_points.txt
inflame-1.0.0.dist-info/top_level.txt
inflame-1.0.0.dist-info/RECORD
