Metadata-Version: 2.1
Name: inflame
Version: 1.0.0
Summary: Convolutional Neural Networks--made easy to reapply to new problems
Home-page: https://github.com/zjohn77/inflame
Author: John Jung
Author-email: tojohnjung@gmail.com
License: MIT
Keywords: deep-learning
Platform: UNKNOWN
Classifier: Programming Language :: Python :: 3
Classifier: License :: OSI Approved :: MIT License
Classifier: Operating System :: POSIX :: Linux
Requires-Dist: scipy (>=1.1)
Requires-Dist: numpy (>=1.15)
Requires-Dist: torch (>=0.4)
Requires-Dist: scikit-learn (>=0.20)
Requires-Dist: gensim (>=3)
Requires-Dist: corpus4classify (>=0.1)
